yhc_pypi/__init__.py
yhc_pypi/yhc_module.py
yhc_pypi-1.0.1.dist-info/METADATA
yhc_pypi-1.0.1.dist-info/WHEEL
yhc_pypi-1.0.1.dist-info/top_level.txt
yhc_pypi-1.0.1.dist-info/RECORD
